divora/__init__.py
divora/divora.py
divora/src/accumulate.py
divora/src/encoder.py
divora/src/load_dataset.py
divora/src/memory_saving_gradients.py
divora/src/model.py
divora/src/sample.py
divora-1.6.dist-info/licenses/LICENSE
divora-1.6.dist-info/METADATA
divora-1.6.dist-info/WHEEL
divora-1.6.dist-info/entry_points.txt
divora-1.6.dist-info/top_level.txt
divora-1.6.dist-info/RECORD
