Metadata-Version: 2.4
Name: divora
Version: 1.6
Summary: A simple way to train and own your AI models. All made possible by Divora Technologies
Home-page: https://divoratech.com
Author: Shiloh Pendergraff
Author-email: shilohpendergraff@gmail.com
License: MIT
Keywords: deep learning,tensorflow,text generation
Requires-Python: >=3.6
License-File: LICENSE
Requires-Dist: tensorflow>=2.5.1
Requires-Dist: regex
Requires-Dist: requests
Requires-Dist: tqdm
Requires-Dist: numpy
Requires-Dist: toposort
Dynamic: author
Dynamic: author-email
Dynamic: description
Dynamic: description-content-type
Dynamic: home-page
Dynamic: keywords
Dynamic: license
Dynamic: license-file
Dynamic: requires-dist
Dynamic: requires-python
Dynamic: summary
